Workbook

Sheet Read Me
A1: Artwork Records — how to use this workbook
A4: TABS
A5: • Artwork Register — your master list. One row per artwork. Start at row 3 (rows 3–4 are filled-in examples you can overwrite or delete).
A6: • Field Guide — explains every column in plain English.
A7: • Summary — live totals (counts, sales, profit). Updates automatically.
A8: • Lists — the menus behind the dropdowns. Edit these to add your own options.
A10: HOW TO START
A11: 1. Give each piece an Inventory ID (RIT-0001, RIT-0002 …) and never reuse one.
A12: 2. Fill left to right. Grey/blue dropdown cells: click the arrow to pick a value.
A13: 3. Leave the AUTO columns alone — they calculate themselves (totals, inches, net, profit, balance).
A14: 4. Add more rows below row 120 if you need them — copy a formula row down so the auto-columns keep working.
A16: TIPS
... A20: • Opens cleanly in LibreOffice Calc; dropdowns, formulas and formatting all carry across.

Sheet Artwork Register
A1: IDENTIFICATION | I1: ARTWORK & STORY | U1: DIMENSIONS | AN1: PRODUCTION COST | AT1: PRICING & SALE | BK1: BUYER / COLLECTOR | BU1: EXHIBITION & PROVENANCE | CA1: LOCATION & INSURANCE | CH1: LOGISTICS & SHIPPING | CT1: DIGITAL / WEB / SEO | DE1: NOTES
A2: Inventory ID | B2: Title | C2: Alternative / Working Title | D2: Series / Collection | E2: Year Created | F2: Date Started | G2: Date Completed | H2: Status | I2: Medium | J2: Support / Substrate | K2: Surface / Texture | L2: Style / Genre | M2: Subject / Theme | N2: Description | O2: Story Behind the Work | P2: Inspiration / Location | Q2: Dominant Colours | R2: Colour Palette / Hex | S2: Keywords / Tags | T2: Orientation | U2: Height (cm) | V2: Width (cm) | W2: Depth (cm) | X2: Height (in) | Y2: Width (in) | Z2: Depth (in) | AA2: Framed? | AB2: Frame Description | AC2: Framed Height (cm) | AD2: Framed Width (cm) | AE2: Framed Depth (cm) | AF2: Weight (kg) | AG2: Edition Type | AH2: Edition Number | AI2: Edition Size | AJ2: Signed? | AK2: Signature Location | AL2: Certificate of Authenticity? | AM2: COA Number | AN2: Materials Cost | AO2: Framing Cost | AP2: Photography Cost | AQ2: Other Costs | AR2: Total Cost to Produce | AS2: Hours Spent | AT2: Currency | AU2: List Price | AV2: Price per sq cm | AW2: Discount | AX2: Sale Price | AY2: Gallery / Platform Fee % | AZ2: Gallery / Platform Fee | BA2: Net to Artist | BB2: Gross Profit | BC2: Tax / GST | BD2: Deposit Paid | BE2: Balance Due | BF2: Payment Method | BG2: Payment Status | BH2: Date Sold | BI2: Invoice Number | BJ2: Sold Through | BK2: Buyer Name | BL2: Buyer Type | BM2: Buyer Email | BN2: Buyer Phone | BO2: Buyer Address / City | BP2: Buyer Country | BQ2: Referred By | BR2: Added to Mailing List? | BS2: Repeat Collector? | BT2: Follow-up Notes | BU2: Exhibited? | BV2: Exhibition History | BW2: Awards / Recognition | BX2: Press / Publications | BY2: Provenance | BZ2: Reproduction / Licensing Rights | CA2: Current Location | CB2: On Loan To | CC2: Loan Return Date | CD2: Insured? | CE2: Insurance Value | CF2: Condition | CG2: Condition Notes | CH2: Packaged Length (cm) | CI2: Packaged Width (cm) | CJ2: Packaged Depth (cm) | CK2: Shipping Weight (kg) | CL2: Crating Required? | CM2: Ready to Hang? | CN2: Hanging Hardware | CO2: Shipping Method | CP2: Shipping Cost | CQ2: Tracking Number | CR2: Date Shipped | CS2: Delivery Confirmed? | CT2: Photographed? | CU2: Image File Name(s) | CV2: Number of Images | CW2: Mockups Created | CX2: URL Slug | CY2: Live Webpage URL | CZ2: Listed Online? | DA2: SEO Meta Title | DB2: SEO Meta Description | DC2: Image Alt Text | DD2: Social Posted? | DE2: General Notes | DF2: Last Updated
A3: RIT-0001 | B3: Coastal Rhythm | D3: Abstract Seascapes | E3: 2025 | G3: 2025-03-14 | H3: Available | I3: Acrylic & oil on canvas | J3: Stretched canvas | L3: Contemporary abstract | M3: Ocean / coast | N3: Layered blues and whites evoking the movement of tide over sand. | O3: Painted after early-morning walks along the coast; captures the meeting of sea and shore. | Q3: Blue, white, sand | S3: abstract seascape, coastal art, blue painting | T3: Landscape | U3: 120 | V3: 150 | W3: 4 | X3: =IF(U3="","",ROUND(U3/2.54,1)) -> 47.2 | Y3: =IF(V3="","",ROUND(V3/2.54,1)) -> 59.1 | Z3: =IF(W3="","",ROUND(W3/2.54,1)) -> 1.6 | AA3: No | AF3: 6.5 | AG3: Original | AJ3: Yes | AK3: Verso | AL3: Yes | AM3: COA-0001 | AN3: 280 | AO3: 0 | AR3: =IF(COUNT(AN3,AO3,AP3,AQ3)=0,"",SUM(AN3:AQ3)) -> 280 | AS3: 40 | AT3: AUD | AU3: 4800 | AV3: =IF(OR(AU3="",U3="",V3=""),"",AU3/(U3*V3)) -> 0.26666667 | AZ3: =IF(OR(AX3="",AY3=""),"",AX3*AY3) | BA3: =IF(AX3="","",AX3-N(AZ3)-N(BC3)) | BB3: =IF(AX3="","",BA3-N(AR3)) | BE3: =IF(AX3="","",AX3-N(BD3)) | BG3: Unpaid | BJ3: Website | CA3: Studio | CD3: Yes | CE3: 4800 | CF3: Excellent | CM3: Yes | CT3: Yes | CX3: coastal-rhythm | CY3: /artwork/coastal-rhythm | CZ3: Yes | DA3: Coastal Rhythm | Abstract Seascape Painting | DF3: 2026-06-25
A4: RIT-0002 | B4: Tidal Memory | D4: Abstract Seascapes | E4: 2024 | G4: 2024-11-02 | H4: Sold | I4: Oil on linen | J4: Belgian linen | L4: Contemporary abstract | M4: Ocean / memory | N4: Soft horizon bands dissolving into texture and light. | Q4: Teal, grey, cream | T4: Landscape | U4: 100 | V4: 100 | W4: 4 | X4: =IF(U4="","",ROUND(U4/2.54,1)) -> 39.4 | Y4: =IF(V4="","",ROUND(V4/2.54,1)) -> 39.4 | Z4: =IF(W4="","",ROUND(W4/2.54,1)) -> 1.6 | AA4: Yes | AB4: Floating oak frame | AF4: 7 | AG4: Original | AJ4: Yes | AN4: 320 | AO4: 250 | AR4: =IF(COUNT(AN4,AO4,AP4,AQ4)=0,"",SUM(AN4:AQ4)) -> 570 | AT4: AUD | AU4: 5200 | AV4: =IF(OR(AU4="",U4="",V4=""),"",AU4/(U4*V4)) -> 0.52 | AX4: 5200 | AY4: 0.3 | AZ4: =IF(OR(AX4="",AY4=""),"",AX4*AY4) -> 1560 | BA4: =IF(AX4="","",AX4-N(AZ4)-N(BC4)) -> 3640 | BB4: =IF(AX4="","",BA4-N(AR4)) -> 3070 | BE4: =IF(AX4="","",AX4-N(BD4)) -> 5200 | BG4: Paid | BH4: 2025-01-20 | BI4: INV-0042 | BJ4: Gallery | BK4: (private collector) | BL4: Collector | BP4: Australia | BR4: Yes | BU4: Yes | BV4: Summer Group Show, Coastal Gallery, 2024 | CA4: Buyer (Sydney) | CF4: Excellent | CT4: Yes | CX4: tidal-memory | CZ4: No | DF4: 2026-06-25
X5: =IF(U5="","",ROUND(U5/2.54,1)) | Y5: =IF(V5="","",ROUND(V5/2.54,1)) | Z5: =IF(W5="","",ROUND(W5/2.54,1)) | AR5: =IF(COUNT(AN5,AO5,AP5,AQ5)=0,"",SUM(AN5:AQ5)) | AV5: =IF(OR(AU5="",U5="",V5=""),"",AU5/(U5*V5)) | AZ5: =IF(OR(AX5="",AY5=""),"",AX5*AY5) | BA5: =IF(AX5="","",AX5-N(AZ5)-N(BC5)) | BB5: =IF(AX5="","",BA5-N(AR5)) | BE5: =IF(AX5="","",AX5-N(BD5))
X6: =IF(U6="","",ROUND(U6/2.54,1)) | Y6: =IF(V6="","",ROUND(V6/2.54,1)) | Z6: =IF(W6="","",ROUND(W6/2.54,1)) | AR6: =IF(COUNT(AN6,AO6,AP6,AQ6)=0,"",SUM(AN6:AQ6)) | AV6: =IF(OR(AU6="",U6="",V6=""),"",AU6/(U6*V6)) | AZ6: =IF(OR(AX6="",AY6=""),"",AX6*AY6) | BA6: =IF(AX6="","",AX6-N(AZ6)-N(BC6)) | BB6: =IF(AX6="","",BA6-N(AR6)) | BE6: =IF(AX6="","",AX6-N(BD6))
X7: =IF(U7="","",ROUND(U7/2.54,1)) | Y7: =IF(V7="","",ROUND(V7/2.54,1)) | Z7: =IF(W7="","",ROUND(W7/2.54,1)) | AR7: =IF(COUNT(AN7,AO7,AP7,AQ7)=0,"",SUM(AN7:AQ7)) | AV7: =IF(OR(AU7="",U7="",V7=""),"",AU7/(U7*V7)) | AZ7: =IF(OR(AX7="",AY7=""),"",AX7*AY7) | BA7: =IF(AX7="","",AX7-N(AZ7)-N(BC7)) | BB7: =IF(AX7="","",BA7-N(AR7)) | BE7: =IF(AX7="","",AX7-N(BD7))
X8: =IF(U8="","",ROUND(U8/2.54,1)) | Y8: =IF(V8="","",ROUND(V8/2.54,1)) | Z8: =IF(W8="","",ROUND(W8/2.54,1)) | AR8: =IF(COUNT(AN8,AO8,AP8,AQ8)=0,"",SUM(AN8:AQ8)) | AV8: =IF(OR(AU8="",U8="",V8=""),"",AU8/(U8*V8)) | AZ8: =IF(OR(AX8="",AY8=""),"",AX8*AY8) | BA8: =IF(AX8="","",AX8-N(AZ8)-N(BC8)) | BB8: =IF(AX8="","",BA8-N(AR8)) | BE8: =IF(AX8="","",AX8-N(BD8))
X9: =IF(U9="","",ROUND(U9/2.54,1)) | Y9: =IF(V9="","",ROUND(V9/2.54,1)) | Z9: =IF(W9="","",ROUND(W9/2.54,1)) | AR9: =IF(COUNT(AN9,AO9,AP9,AQ9)=0,"",SUM(AN9:AQ9)) | AV9: =IF(OR(AU9="",U9="",V9=""),"",AU9/(U9*V9)) | AZ9: =IF(OR(AX9="",AY9=""),"",AX9*AY9) | BA9: =IF(AX9="","",AX9-N(AZ9)-N(BC9)) | BB9: =IF(AX9="","",BA9-N(AR9)) | BE9: =IF(AX9="","",AX9-N(BD9))
X10: =IF(U10="","",ROUND(U10/2.54,1)) | Y10: =IF(V10="","",ROUND(V10/2.54,1)) | Z10: =IF(W10="","",ROUND(W10/2.54,1)) | AR10: =IF(COUNT(AN10,AO10,AP10,AQ10)=0,"",SUM(AN10:AQ10)) | AV10: =IF(OR(AU10="",U10="",V10=""),"",AU10/(U10*V10)) | AZ10: =IF(OR(AX10="",AY10=""),"",AX10*AY10) | BA10: =IF(AX10="","",AX10-N(AZ10)-N(BC10)) | BB10: =IF(AX10="","",BA10-N(AR10)) | BE10: =IF(AX10="","",AX10-N(BD10))
X11: =IF(U11="","",ROUND(U11/2.54,1)) | Y11: =IF(V11="","",ROUND(V11/2.54,1)) | Z11: =IF(W11="","",ROUND(W11/2.54,1)) | AR11: =IF(COUNT(AN11,AO11,AP11,AQ11)=0,"",SUM(AN11:AQ11)) | AV11: =IF(OR(AU11="",U11="",V11=""),"",AU11/(U11*V11)) | AZ11: =IF(OR(AX11="",AY11=""),"",AX11*AY11) | BA11: =IF(AX11="","",AX11-N(AZ11)-N(BC11)) | BB11: =IF(AX11="","",BA11-N(AR11)) | BE11: =IF(AX11="","",AX11-N(BD11))
X12: =IF(U12="","",ROUND(U12/2.54,1)) | Y12: =IF(V12="","",ROUND(V12/2.54,1)) | Z12: =IF(W12="","",ROUND(W12/2.54,1)) | AR12: =IF(COUNT(AN12,AO12,AP12,AQ12)=0,"",SUM(AN12:AQ12)) | AV12: =IF(OR(AU12="",U12="",V12=""),"",AU12/(U12*V12)) | AZ12: =IF(OR(AX12="",AY12=""),"",AX12*AY12) | BA12: =IF(AX12="","",AX12-N(AZ12)-N(BC12)) | BB12: =IF(AX12="","",BA12-N(AR12)) | BE12: =IF(AX12="","",AX12-N(BD12))
X13: =IF(U13="","",ROUND(U13/2.54,1)) | Y13: =IF(V13="","",ROUND(V13/2.54,1)) | Z13: =IF(W13="","",ROUND(W13/2.54,1)) | AR13: =IF(COUNT(AN13,AO13,AP13,AQ13)=0,"",SUM(AN13:AQ13)) | AV13: =IF(OR(AU13="",U13="",V13=""),"",AU13/(U13*V13)) | AZ13: =IF(OR(AX13="",AY13=""),"",AX13*AY13) | BA13: =IF(AX13="","",AX13-N(AZ13)-N(BC13)) | BB13: =IF(AX13="","",BA13-N(AR13)) | BE13: =IF(AX13="","",AX13-N(BD13))
X14: =IF(U14="","",ROUND(U14/2.54,1)) | Y14: =IF(V14="","",ROUND(V14/2.54,1)) | Z14: =IF(W14="","",ROUND(W14/2.54,1)) | AR14: =IF(COUNT(AN14,AO14,AP14,AQ14)=0,"",SUM(AN14:AQ14)) | AV14: =IF(OR(AU14="",U14="",V14=""),"",AU14/(U14*V14)) | AZ14: =IF(OR(AX14="",AY14=""),"",AX14*AY14) | BA14: =IF(AX14="","",AX14-N(AZ14)-N(BC14)) | BB14: =IF(AX14="","",BA14-N(AR14)) | BE14: =IF(AX14="","",AX14-N(BD14))
X15: =IF(U15="","",ROUND(U15/2.54,1)) | Y15: =IF(V15="","",ROUND(V15/2.54,1)) | Z15: =IF(W15="","",ROUND(W15/2.54,1)) | AR15: =IF(COUNT(AN15,AO15,AP15,AQ15)=0,"",SUM(AN15:AQ15)) | AV15: =IF(OR(AU15="",U15="",V15=""),"",AU15/(U15*V15)) | AZ15: =IF(OR(AX15="",AY15=""),"",AX15*AY15) | BA15: =IF(AX15="","",AX15-N(AZ15)-N(BC15)) | BB15: =IF(AX15="","",BA15-N(AR15)) | BE15: =IF(AX15="","",AX15-N(BD15))
X16: =IF(U16="","",ROUND(U16/2.54,1)) | Y16: =IF(V16="","",ROUND(V16/2.54,1)) | Z16: =IF(W16="","",ROUND(W16/2.54,1)) | AR16: =IF(COUNT(AN16,AO16,AP16,AQ16)=0,"",SUM(AN16:AQ16)) | AV16: =IF(OR(AU16="",U16="",V16=""),"",AU16/(U16*V16)) | AZ16: =IF(OR(AX16="",AY16=""),"",AX16*AY16) | BA16: =IF(AX16="","",AX16-N(AZ16)-N(BC16)) | BB16: =IF(AX16="","",BA16-N(AR16)) | BE16: =IF(AX16="","",AX16-N(BD16))
... X120: =IF(U120="","",ROUND(U120/2.54,1)) | Y120: =IF(V120="","",ROUND(V120/2.54,1)) | Z120: =IF(W120="","",ROUND(W120/2.54,1)) | AR120: =IF(COUNT(AN120,AO120,AP120,AQ120)=0,"",SUM(AN120:AQ120)) | AV120: =IF(OR(AU120="",U120="",V120=""),"",AU120/(U120*V120)) | AZ120: =IF(OR(AX120="",AY120=""),"",AX120*AY120) | BA120: =IF(AX120="","",AX120-N(AZ120)-N(BC120)) | BB120: =IF(AX120="","",BA120-N(AR120)) | BE120: =IF(AX120="","",AX120-N(BD120))

Sheet Field Guide
A1: Field Guide — what to put in each column
A2: Every column in the Artwork Register, grouped, with a plain-English note on what it's for.
A4: # | B4: Column | C4: Group | D4: What to enter / why it matters
A5: 1 | B5: Inventory ID | C5: IDENTIFICATION | D5: Unique code for each piece (e.g. RIT-0001). Your master key — never reuse a number.
A6: 2 | B6: Title | C6: IDENTIFICATION | D6: The artwork's name as you'd show it publicly.
A7: 3 | B7: Alternative / Working Title | C7: IDENTIFICATION | D7: Studio nickname or earlier title, for your own searching.
A8: 4 | B8: Series / Collection | C8: IDENTIFICATION | D8: Which body of work / collection it belongs to (links to a collection page).
A9: 5 | B9: Year Created | C9: IDENTIFICATION | D9: Year the work was finished — used on labels, certificates and listings.
A10: 6 | B10: Date Started | C10: IDENTIFICATION | D10: When you began the piece.
A11: 7 | B11: Date Completed | C11: IDENTIFICATION | D11: When you signed it off. Drives 'newest work' sorting.
A12: 8 | B12: Status | C12: IDENTIFICATION | D12: Current state — Available, Sold, Reserved, Commission, etc. Pick from dropdown.
A13: 9 | B13: Medium | C13: ARTWORK & STORY | D13: Materials used, e.g. 'Acrylic & oil on canvas'.
A14: 10 | B14: Support / Substrate | C14: ARTWORK & STORY | D14: What it's painted on — canvas, linen, board, paper.
A15: 11 | B15: Surface / Texture | C15: ARTWORK & STORY | D15: Finish notes — heavy impasto, smooth, varnished, matte.
A16: 12 | B16: Style / Genre | C16: ARTWORK & STORY | D16: e.g. Contemporary abstract, abstract landscape.
... A114: 110 | B114: Last Updated | C114: NOTES | D114: Date you last edited this row.

Sheet Summary
A1: Collection Summary
A2: Live totals — updates automatically as you fill in the Register.
A4: Metric | B4: Value
A5: Total artworks logged | B5: =COUNTA('Artwork Register'!$B$3:$B$120) -> 2
A6: Available | B6: =COUNTIF('Artwork Register'!$H$3:$H$120,"Available") -> 1
A7: Reserved | B7: =COUNTIF('Artwork Register'!$H$3:$H$120,"Reserved") -> 0
A8: Sold | B8: =COUNTIF('Artwork Register'!$H$3:$H$120,"Sold") -> 1
A9: On Loan | B9: =COUNTIF('Artwork Register'!$H$3:$H$120,"On Loan") -> 0
A10: Not For Sale | B10: =COUNTIF('Artwork Register'!$H$3:$H$120,"Not For Sale") -> 0
A12: Total value of available works (List Price) | B12: =SUMIF('Artwork Register'!$H$3:$H$120,"Available",'Artwork Register'!$AU$3:$AU$120) -> 4800
A13: Total sales (Sale Price) | B13: =SUM('Artwork Register'!$AX$3:$AX$120) -> 5200
A14: Total net to artist | B14: =SUM('Artwork Register'!$BA$3:$BA$120) -> 3640
A15: Total cost to produce (all) | B15: =SUM('Artwork Register'!$AR$3:$AR$120) -> 850
A16: Total gross profit (sold) | B16: =SUM('Artwork Register'!$BB$3:$BB$120) -> 3070
A17: Average sale price | B17: =IFERROR(AVERAGEIF('Artwork Register'!$AX$3:$AX$120,">0"),0) -> 5200

Sheet Lists
A1: DROPDOWN REFERENCE LISTS — edit these to change menu options in the Register
A2: Status | B2: Orientation | C2: EditionType | D2: YesNo | E2: BuyerType | F2: SoldThrough | G2: PaymentStatus | H2: PaymentMethod | I2: Currency | J2: Condition | K2: ShippingMethod
A3: Available | B3: Landscape | C3: Original | D3: Yes | E3: Collector | F3: Website | G3: Unpaid | H3: Bank Transfer | I3: AUD | J3: Excellent | K3: Courier
A4: Reserved | B4: Portrait | C4: Limited Edition Print | D4: No | E4: Interior Designer | F4: Gallery | G4: Deposit Paid | H4: Credit Card | I4: USD | J4: Very Good | K4: Art Freight / Specialist
A5: Sold | B5: Square | C5: Open Edition Print | E5: Architect | F5: Art Fair | G5: Paid in Full | H5: PayPal | I5: GBP | J5: Good | K5: Australia Post
A6: On Hold | B6: Panoramic | C6: Diptych | E6: Property Developer | F6: Studio / Direct | G6: Payment Plan | H6: Cash | I6: EUR | J6: Minor Damage | K6: Hand Delivery
A7: Commission - In Progress | C7: Triptych | E7: Luxury Homeowner | F7: Instagram / Social | G7: Refunded | H7: Afterpay / Instalment | I7: NZD | J7: Needs Restoration | K7: Local Pickup
A8: Commission - Delivered | C8: Study | E8: Art Consultant | F8: Agent | H8: Art Money | I8: CAD | J8: Damaged | K8: International Freight
A9: On Loan | E9: Buyer's Agent | F9: Online Marketplace | H9: Other
A10: Not For Sale | E10: Corporate Buyer | F10: Commission
A11: Gifted | E11: Gallery / Curator | F11: Other
A12: Archived | E12: Other
A13: Donated
A14: Destroyed/Lost
